haesleinhuepf_pyqode.python-2.15.2-py3.8-nspkg.pth
pyqode/python/__init__.py
pyqode/python/designer_plugin.py
pyqode/python/folding.py
pyqode/python/_forms/__init__.py
pyqode/python/_forms/pyqode_python_icons_rc.py
pyqode/python/backend/__init__.py
pyqode/python/backend/pep8utils.py
pyqode/python/backend/server.py
pyqode/python/backend/workers.py
pyqode/python/managers/__init__.py
pyqode/python/managers/file.py
pyqode/python/modes/__init__.py
pyqode/python/modes/autocomplete.py
pyqode/python/modes/autoindent.py
pyqode/python/modes/calltips.py
pyqode/python/modes/comments.py
pyqode/python/modes/frosted_checker.py
pyqode/python/modes/goto_assignements.py
pyqode/python/modes/indenter.py
pyqode/python/modes/pep8_checker.py
pyqode/python/modes/sh.py
pyqode/python/panels/__init__.py
pyqode/python/panels/quick_doc.py
pyqode/python/panels/symbol_browser.py
pyqode/python/widgets/__init__.py
pyqode/python/widgets/code_edit.py
pyqode/python/widgets/console.py
pyqode/python/widgets/interactive.py
pyqode/python/widgets/outline.py
haesleinhuepf_pyqode.python-2.15.2.dist-info/AUTHORS.rst
haesleinhuepf_pyqode.python-2.15.2.dist-info/LICENSE
haesleinhuepf_pyqode.python-2.15.2.dist-info/METADATA
haesleinhuepf_pyqode.python-2.15.2.dist-info/WHEEL
haesleinhuepf_pyqode.python-2.15.2.dist-info/entry_points.txt
haesleinhuepf_pyqode.python-2.15.2.dist-info/namespace_packages.txt
haesleinhuepf_pyqode.python-2.15.2.dist-info/top_level.txt
haesleinhuepf_pyqode.python-2.15.2.dist-info/RECORD
