Metadata-Version: 2.1
Name: haesleinhuepf-pyqode.python
Version: 2.15.2
Summary: Adds python support to pyqode.core
Home-page: https://github.com/haesleinhuepf/pyqode.python
Author: Robert Haase, Colin Duquesnoy
Author-email: robert.haase@tu-dresden.de
License: MIT
Keywords: CodeEdit PySide PyQt code editor widget python
Platform: UNKNOWN
Classifier: Development Status :: 5 - Production/Stable
Classifier: Environment :: X11 Applications :: Qt
Classifier: Environment :: Win32 (MS Windows)
Classifier: Intended Audience :: Developers
Classifier: License :: OSI Approved :: MIT License
Classifier: Operating System :: Microsoft :: Windows
Classifier: Operating System :: POSIX :: Linux
Classifier: Programming Language :: Python :: 2.7
Classifier: Programming Language :: Python :: 3.2
Classifier: Programming Language :: Python :: 3.3
Classifier: Programming Language :: Python :: 3.4
Classifier: Programming Language :: Python :: 3.5
Classifier: Programming Language :: Python :: 3.6
Classifier: Programming Language :: Python :: 3.7
Classifier: Topic :: Software Development :: Libraries :: Application Frameworks
Classifier: Topic :: Software Development :: Widget Sets
Classifier: Topic :: Text Editors :: Integrated Development Environments (IDE)
License-File: LICENSE
License-File: AUTHORS.rst
Requires-Dist: haesleinhuepf-pyqode.core
Requires-Dist: jedi
Requires-Dist: pycodestyle
Requires-Dist: pyflakes
Requires-Dist: docutils
